requirements.txt
setup.py
django_asyncio_task_queue/__init__.py
django_asyncio_task_queue/apps.py
django_asyncio_task_queue/utils.py
django_asyncio_task_queue.egg-info/PKG-INFO
django_asyncio_task_queue.egg-info/SOURCES.txt
django_asyncio_task_queue.egg-info/dependency_links.txt
django_asyncio_task_queue.egg-info/top_level.txt
django_asyncio_task_queue/admin/__init__.py
django_asyncio_task_queue/admin/config.py
django_asyncio_task_queue/admin/debug.py
django_asyncio_task_queue/admin/error.py
django_asyncio_task_queue/admin/stat.py
django_asyncio_task_queue/admin/task.py
django_asyncio_task_queue/management/__init__.py
django_asyncio_task_queue/management/base.py
django_asyncio_task_queue/management/commands/__init__.py
django_asyncio_task_queue/management/commands/asyncio_task_queue_stat.py
django_asyncio_task_queue/management/commands/asyncio_task_queue_worker.py
django_asyncio_task_queue/migrations/0001_initial.py
django_asyncio_task_queue/migrations/__init__.py
django_asyncio_task_queue/models/__init__.py
django_asyncio_task_queue/models/abstract_config.py
django_asyncio_task_queue/models/abstract_debug.py
django_asyncio_task_queue/models/abstract_error.py
django_asyncio_task_queue/models/abstract_stat.py
django_asyncio_task_queue/models/abstract_task.py
django_asyncio_task_queue/models/asyncio_task_queue_config.py
django_asyncio_task_queue/models/asyncio_task_queue_debug.py
django_asyncio_task_queue/models/asyncio_task_queue_error.py
django_asyncio_task_queue/models/asyncio_task_queue_stat.py