Metadata-Version: 2.1
Name: django-asyncio-task-queue
Version: 2021.4.29
Summary: Django asyncio task queue
Home-page: https://github.com/git/django-asyncio-task-queue.py
License: Unlicense
Keywords: django asyncio task queue
Platform: UNKNOWN
Classifier: Framework :: Django
Classifier: License :: Public Domain
Classifier: Operating System :: OS Independent
Classifier: Programming Language :: Python :: 3
